{
  "r.l.u-技术自由主义-自由主义威权派": [
    {
      "id": "rlu_1",
      "question": "您认为应该由技术专家治理社会吗？",
      "options": [
        {
          "text": "是",
          "ideology_scores": {
            "技术威权主义": 10,
            "数字威权主义": 10,
            "算法治理": 10,
            "技术治理": 10,
            "数据威权主义": 10,
            "智能威权主义": 10,
            "科技威权主义": 10,
            "数字治理": 8,
            "算法威权主义": 10,
            "智能治理": 8
          }
        },
        {
          "text": "中立",
          "ideology_scores": {
            "技术威权主义": 4,
            "数字威权主义": 4,
            "算法治理": 4,
            "技术治理": 4,
            "数据威权主义": 4,
            "智能威权主义": 4,
            "科技威权主义": 4,
            "数字治理": 6,
            "算法威权主义": 4,
            "智能治理": 6
          }
        },
        {
          "text": "否",
          "ideology_scores": {
            "技术威权主义": -10,
            "数字威权主义": -10,
            "算法治理": -10,
            "技术治理": -10,
            "数据威权主义": -10,
            "智能威权主义": -10,
            "科技威权主义": -10,
            "数字治理": -8,
            "算法威权主义": -10,
            "智能治理": -8
          }
        }
      ]
    },
    {
      "id": "rlu_2",
      "question": "您支持通过技术手段监控和管理社会吗？",
      "options": [
        {
          "text": "是",
          "ideology_scores": {
            "技术威权主义": 10,
            "数字威权主义": 10,
            "算法治理": 8,
            "技术治理": 8,
            "数据威权主义": 10,
            "智能威权主义": 10,
            "科技威权主义": 10,
            "数字治理": 8,
            "算法威权主义": 10,
            "智能治理": 8
          }
        },
        {
          "text": "中立",
          "ideology_scores": {
            "技术威权主义": 4,
            "数字威权主义": 4,
            "算法治理": 6,
            "技术治理": 6,
            "数据威权主义": 4,
            "智能威权主义": 4,
            "科技威权主义": 4,
            "数字治理": 6,
            "算法威权主义": 4,
            "智能治理": 6
          }
        },
        {
          "text": "否",
          "ideology_scores": {
            "技术威权主义": -10,
            "数字威权主义": -10,
            "算法治理": -8,
            "技术治理": -8,
            "数据威权主义": -10,
            "智能威权主义": -10,
            "科技威权主义": -10,
            "数字治理": -8,
            "算法威权主义": -10,
            "智能治理": -8
          }
        }
      ]
    },
    {
      "id": "rlu_3",
      "question": "您认为技术进步应该优先于个人隐私吗？",
      "options": [
        {
          "text": "是",
          "ideology_scores": {
            "技术威权主义": 10,
            "数字威权主义": 10,
            "算法治理": 8,
            "技术治理": 8,
            "数据威权主义": 10,
            "智能威权主义": 10,
            "科技威权主义": 10,
            "数字治理": 6,
            "算法威权主义": 10,
            "智能治理": 6
          }
        },
        {
          "text": "中立",
          "ideology_scores": {
            "技术威权主义": 4,
            "数字威权主义": 4,
            "算法治理": 6,
            "技术治理": 6,
            "数据威权主义": 4,
            "智能威权主义": 4,
            "科技威权主义": 4,
            "数字治理": 8,
            "算法威权主义": 4,
            "智能治理": 8
          }
        },
        {
          "text": "否",
          "ideology_scores": {
            "技术威权主义": -10,
            "数字威权主义": -10,
            "算法治理": -8,
            "技术治理": -8,
            "数据威权主义": -10,
            "智能威权主义": -10,
            "科技威权主义": -10,
            "数字治理": -6,
            "算法威权主义": -10,
            "智能治理": -6
          }
        }
      ]
    },
    {
      "id": "rlu_4",
      "question": "您支持通过算法和AI来优化社会决策吗？",
      "options": [
        {
          "text": "是",
          "ideology_scores": {
            "技术威权主义": 8,
            "数字威权主义": 8,
            "算法治理": 10,
            "技术治理": 10,
            "数据威权主义": 8,
            "智能威权主义": 8,
            "科技威权主义": 8,
            "数字治理": 10,
            "算法威权主义": 8,
            "智能治理": 10
          }
        },
        {
          "text": "中立",
          "ideology_scores": {
            "技术威权主义": 6,
            "数字威权主义": 6,
            "算法治理": 4,
            "技术治理": 4,
            "数据威权主义": 6,
            "智能威权主义": 6,
            "科技威权主义": 6,
            "数字治理": 4,
            "算法威权主义": 6,
            "智能治理": 4
          }
        },
        {
          "text": "否",
          "ideology_scores": {
            "技术威权主义": -8,
            "数字威权主义": -8,
            "算法治理": -10,
            "技术治理": -10,
            "数据威权主义": -8,
            "智能威权主义": -8,
            "科技威权主义": -8,
            "数字治理": -10,
            "算法威权主义": -8,
            "智能治理": -10
          }
        }
      ]
    },
    {
      "id": "rlu_5",
      "question": "您认为应该通过技术手段实现社会控制吗？",
      "options": [
        {
          "text": "是",
          "ideology_scores": {
            "技术威权主义": 10,
            "数字威权主义": 10,
            "算法治理": 8,
            "技术治理": 8,
            "数据威权主义": 10,
            "智能威权主义": 10,
            "科技威权主义": 10,
            "数字治理": 6,
            "算法威权主义": 10,
            "智能治理": 6
          }
        },
        {
          "text": "中立",
          "ideology_scores": {
            "技术威权主义": 4,
            "数字威权主义": 4,
            "算法治理": 6,
            "技术治理": 6,
            "数据威权主义": 4,
            "智能威权主义": 4,
            "科技威权主义": 4,
            "数字治理": 8,
            "算法威权主义": 4,
            "智能治理": 8
          }
        },
        {
          "text": "否",
          "ideology_scores": {
            "技术威权主义": -10,
            "数字威权主义": -10,
            "算法治理": -8,
            "技术治理": -8,
            "数据威权主义": -10,
            "智能威权主义": -10,
            "科技威权主义": -10,
            "数字治理": -6,
            "算法威权主义": -10,
            "智能治理": -6
          }
        }
      ]
    }
  ]
}